PyCodeCommenter/__init__.py
PyCodeCommenter/cli.py
PyCodeCommenter/commenter.py
PyCodeCommenter/coverage.py
PyCodeCommenter/docstring_parser.py
PyCodeCommenter/parameter_descriptions.py
PyCodeCommenter/templates.py
PyCodeCommenter/type_analyzer.py
PyCodeCommenter/validator.py
pycodecommenter-2.0.3.dist-info/licenses/LICENSE
pycodecommenter-2.0.3.dist-info/METADATA
pycodecommenter-2.0.3.dist-info/WHEEL
pycodecommenter-2.0.3.dist-info/entry_points.txt
pycodecommenter-2.0.3.dist-info/top_level.txt
pycodecommenter-2.0.3.dist-info/RECORD
