Metadata-Version: 2.4
Name: pycodecommenter
Version: 2.0.3
Summary: Automatically generate, validate, and maintain Google-style docstrings for Python code
Author-email: Amos Quety <amosnabasa4@gmail.com>
License: MIT
Project-URL: Homepage, https://github.com/AmosQuety/PyCodeCommenter
Project-URL: Documentation, https://github.com/AmosQuety/PyCodeCommenter/blob/main/README.md
Project-URL: Repository, https://github.com/AmosQuety/PyCodeCommenter
Project-URL: Bug Tracker, https://github.com/AmosQuety/PyCodeCommenter/issues
Keywords: documentation,docstring,validation,coverage,python
Classifier: Development Status :: 4 - Beta
Classifier: Intended Audience :: Developers
Classifier: License :: OSI Approved :: MIT License
Classifier: Programming Language :: Python :: 3
Classifier: Programming Language :: Python :: 3.8
Classifier: Programming Language :: Python :: 3.9
Classifier: Programming Language :: Python :: 3.10
Classifier: Programming Language :: Python :: 3.11
Classifier: Programming Language :: Python :: 3.12
Classifier: Topic :: Software Development :: Documentation
Classifier: Topic :: Software Development :: Quality Assurance
Requires-Python: >=3.8
License-File: LICENSE
Provides-Extra: dev
Requires-Dist: pytest>=7.0; extra == "dev"
Requires-Dist: pytest-cov>=4.0; extra == "dev"
Requires-Dist: black>=23.0; extra == "dev"
Requires-Dist: flake8>=6.0; extra == "dev"
Dynamic: license-file
